facebook_scribe-2.0.post1.dist-info/DESCRIPTION.rst
facebook_scribe-2.0.post1.dist-info/METADATA
facebook_scribe-2.0.post1.dist-info/RECORD
facebook_scribe-2.0.post1.dist-info/WHEEL
facebook_scribe-2.0.post1.dist-info/metadata.json
facebook_scribe-2.0.post1.dist-info/top_level.txt
fb303/FacebookService.py
fb303/__init__.py
fb303/constants.py
fb303/ttypes.py
scribe/__init__.py
scribe/constants.py
scribe/scribe.py
scribe/ttypes.py
