Metadata-Version: 2.0
Name: facebook-scribe
Version: 2.0.post1
Summary: A Python client for Facebook Scribe
Home-page: http://github.com/tomprimozic/scribe-python/
Author: Tom Primozic
Author-email: tom.primozic@zemanta.com
License: UNKNOWN
Platform: UNKNOWN
Requires-Dist: thrift (>=0.9.0)
